{
  "1": {
    "trackerIp": "127.0.0.1",
    "magnetText": "asjdhkajshdalks333333dhlaskd",
    "mateaInfo": {
      "name": "dummy.txt",
      "length": 1298787,
      "piece length": 524288,
      "pieces": [
        "f5a52f813e65bb0647742dde77c9ee22a78c5889a90e39bfd33568da0a0ad2dd",
        "98a350d58c808fa08558c4a04da4597755c50f5d15f647187f166cd3f4decc3a",
        "16cb4241acb8918ad72decac2498802315c1f3af6a28644fb16fabb61640a97c"
      ]
    }
  },

  "2": {
    "trackerIp": "127.0.0.1",
    "magnetText": "asjdhkajshdalks333333dhlaskd",
    "metaInfo": {
      "name": "dummy.txt",
      "length": 1298787,
      "piece length": 524288,
      "pieces": [
        "187263918723619827361982",
        "17263918723619287361238712",
        "127381723018237012ajksd"
      ]
    }
  }
}
